Firefly/Firefly
Firefly/__init__.py
Firefly/index.html
Firefly/run_server.py
Firefly/server.py
Firefly/bin/Firefly
Firefly/bin/make_new_repo.sh
Firefly/data_reader/FIREreader.py
Firefly/data_reader/__init__.py
Firefly/data_reader/json_utils.py
Firefly/data_reader/particlegroup.py
Firefly/data_reader/reader.py
Firefly/data_reader/settings.py
Firefly/data_reader/tween.py
Firefly/ntbks/convert_FIRE_data.ipynb
Firefly/ntbks/exampleSettings.json
Firefly/ntbks/flask_tutorial.ipynb
Firefly/ntbks/minimal_example.ipynb
Firefly/ntbks/multiple_datasets_tutorial.ipynb
Firefly/ntbks/reader_tutorial.ipynb
Firefly/ntbks/settings_tutorial.ipynb
Firefly/ntbks/tween_test.ipynb
Firefly/ntbks/.ipynb_checkpoints/Untitled-checkpoint.ipynb
Firefly/ntbks/.ipynb_checkpoints/convert_FIRE_data-checkpoint.ipynb
Firefly/ntbks/.ipynb_checkpoints/customOptions-checkpoint.ipynb
Firefly/ntbks/.ipynb_checkpoints/flask_tutorial-checkpoint.ipynb
Firefly/ntbks/.ipynb_checkpoints/multiple_datasets_tutorial-checkpoint.ipynb
Firefly/ntbks/.ipynb_checkpoints/mySettings-checkpoint.json
Firefly/ntbks/.ipynb_checkpoints/reader_tutorial-checkpoint.ipynb
Firefly/ntbks/.ipynb_checkpoints/settings_tutorial-checkpoint.ipynb
Firefly/ntbks/.ipynb_checkpoints/tween_test-checkpoint.ipynb
Firefly/ntbks/py_conversions/convert_FIRE_data.py
Firefly/ntbks/py_conversions/flask_tutorial.py
Firefly/ntbks/py_conversions/multiple_datasets_tutorial.py
Firefly/ntbks/py_conversions/reader_tutorial.py
Firefly/ntbks/py_conversions/settings_tutorial.py
Firefly/static/css/UIStyles.css
Firefly/static/css/UIStyles2.css
Firefly/static/css/mainStyles.css
Firefly/static/data/startup.json
Firefly/static/data/FIREData_50/DataGas000.json
Firefly/static/data/FIREData_50/DataGas001.json
Firefly/static/data/FIREData_50/DataGas002.json
Firefly/static/data/FIREData_50/DataGas003.json
Firefly/static/data/FIREData_50/DataGas004.json
Firefly/static/data/FIREData_50/DataGas005.json
Firefly/static/data/FIREData_50/DataGas006.json
Firefly_vis-2.0.4.dist-info/LICENSE
Firefly_vis-2.0.4.dist-info/METADATA
Firefly_vis-2.0.4.dist-info/WHEEL
Firefly_vis-2.0.4.dist-info/top_level.txt
Firefly_vis-2.0.4.dist-info/RECORD
