Metadata-Version: 2.1
Name: Firefly-vis
Version: 2.0.4
Summary: A browser-based particle visualization platform
Home-page: https://github.com/ageller/Firefly
Author: Alex Gurvich, Aaron Geller
Author-email: agurvich@u.northwestern.edu, ageller@northwestern.edu
License: UNKNOWN
Project-URL: Bug Tracker, https://github.com/ageller/Firefly/issues
Platform: UNKNOWN
Classifier: Programming Language :: Python :: 3
Classifier: License :: OSI Approved :: MIT License
Classifier: Operating System :: OS Independent
Requires-Python: >=3.6
License-File: LICENSE
Requires-Dist: numpy
Requires-Dist: h5py
Requires-Dist: pandas
Requires-Dist: eventlet
Requires-Dist: flask-socketio
Requires-Dist: flask
Requires-Dist: requests
Requires-Dist: abg-python (>=1.0.2)
